.coveragerc
CODE_OF_CONDUCT.md
LICENSE
MANIFEST.in
README.md
pyproject.toml
requirements-dev.txt
setup.cfg
setup.py
InkT.egg-info/PKG-INFO
InkT.egg-info/SOURCES.txt
InkT.egg-info/dependency_links.txt
InkT.egg-info/not-zip-safe
InkT.egg-info/top_level.txt
docs/Makefile
docs/RELEASE.rst
docs/conf.py
docs/examples.rst
docs/index.rst
docs/make.bat
docs/reference.rst
docs/_static/favicon.ico
docs/_static/logo.png
docs/_templates/autosummary/class.rst
docs/_templates/autosummary/module.rst
docs/reference/manimpango.Layout.rst
docs/reference/manimpango.MarkupUtils.rst
docs/reference/manimpango.PangoUtils.rst
docs/reference/manimpango.TextSetting.rst
docs/reference/manimpango.attributes.TextAttribute.rst
docs/reference/manimpango.exceptions.MarkupParseError.rst
docs/reference/manimpango.fonts.FontDescription.rst
docs/reference/manimpango.fonts.enums.Style.rst
docs/reference/manimpango.fonts.enums.Variant.rst
docs/reference/manimpango.fonts.enums.Weight.rst
docs/reference/manimpango.fonts.enums.rst
docs/reference/manimpango.list_fonts.rst
docs/reference/manimpango.register_font.rst
docs/reference/manimpango.renderer.ImageRenderer.rst
docs/reference/manimpango.renderer.SVGRenderer.rst
docs/reference/manimpango.text2svg.rst
docs/reference/manimpango.unregister_font.rst
inkt.egg-info/PKG-INFO
inkt.egg-info/SOURCES.txt
inkt.egg-info/dependency_links.txt
inkt.egg-info/not-zip-safe
inkt.egg-info/top_level.txt
manimpango/__init__.py
manimpango/_distributor_init.py
manimpango/_version.py
manimpango/cmanimpango.c
manimpango/cmanimpango.pxd
manimpango/cmanimpango.pyx
manimpango/enums.c
manimpango/enums.pyx
manimpango/exceptions.py
manimpango/register_font.c
manimpango/register_font.pxd
manimpango/register_font.pyx
manimpango/attributes/__init__.py
manimpango/fonts/__init__.py
manimpango/fonts/_font_desc.c
manimpango/fonts/_font_desc.pxd
manimpango/fonts/_font_desc.pyi
manimpango/fonts/_font_desc.pyx
manimpango/fonts/enums.c
manimpango/fonts/enums.pyi
manimpango/fonts/enums.pyx
manimpango/include/cairo.pxd
manimpango/include/glib.pxd
manimpango/include/pango.pxd
manimpango/include/pango_attributes.pxd
manimpango/layout/__init__.py
manimpango/layout/_layout.c
manimpango/layout/_layout.pyx
manimpango/renderer/__init__.py
manimpango/renderer/image_renderer.c
