Metadata-Version: 2.1
Name: InkT
Version: 0.0.1a1
Summary: Bindings for Pango for using with Manim.
Home-page: https://manimpango.manim.community/
Author: Naveen M K
Author-email: naveen@manim.community
Maintainer: The Manim Community Developers
License: MIT
Project-URL: Documentation, https://manimpango.manim.community/
Project-URL: Source, https://github.com/ManimCommunity/manimpango
Project-URL: Release notes, https://github.com/ManimCommunity/ManimPango/releases/
Keywords: cython,pango,cairo,manim
Platform: Linux
Platform: macOS
Platform: Windows
Classifier: Programming Language :: Python :: 3
Classifier: Programming Language :: Python :: 3.7
Classifier: Programming Language :: Python :: 3.8
Classifier: Programming Language :: Python :: 3.9
Classifier: Programming Language :: Python :: 3.10
Classifier: Development Status :: 4 - Beta
Classifier: Programming Language :: Python :: 3 :: Only
Classifier: License :: OSI Approved :: MIT License
Classifier: Operating System :: OS Independent
Classifier: Programming Language :: Cython
Requires-Python: >=3.8
License-File: LICENSE
